htmx_forms/__init__.py
htmx_forms/apps.py
htmx_forms/conf.py
htmx_forms/forms.py
htmx_forms/views.py
htmx_forms/static/htmx_forms.css
htmx_forms/static/htmx_forms.js
htmx_forms/templates/htmx_forms/base.html
htmx_forms/templates/htmx_forms/dialogs.html
htmx_forms/templates/htmx_forms/generic_form.html
htmx_forms/templates/htmx_forms/generic_form_inner.html
htmx_forms/templates/htmx_forms/overlay.html
htmx_forms/templates/htmx_forms/form/form_field.html
htmx_forms/templatetags/__init__.py
htmx_forms/templatetags/htmx_forms_tags.py
django_htmx_forms-0.1.5.dist-info/METADATA
django_htmx_forms-0.1.5.dist-info/WHEEL
django_htmx_forms-0.1.5.dist-info/top_level.txt
django_htmx_forms-0.1.5.dist-info/RECORD
