Metadata-Version: 2.4
Name: django-htmx-forms
Version: 0.1.5
Summary: A Django helper app to add editing capabilities to the frontend using Django, HTMX and modal forms.
Home-page: http://github.com/morlandi/django-htmx-forms
Author: Mario Orlandi
Author-email: morlandi@brainstorm.it
License: MIT
Classifier: Development Status :: 4 - Beta
Classifier: Operating System :: OS Independent
Classifier: Programming Language :: Python
Classifier: Framework :: Django
Classifier: Framework :: Django :: 5.0
Classifier: Intended Audience :: Developers
Classifier: License :: OSI Approved :: BSD License
Classifier: Natural Language :: English
Classifier: Programming Language :: Python :: 3.12
Dynamic: author
Dynamic: author-email
Dynamic: classifier
Dynamic: description
Dynamic: description-content-type
Dynamic: home-page
Dynamic: license
Dynamic: summary
